{
    "BuildID": "e62ff478-ae3d-481f-a0e3-a6ddba86f66a",
    "Command": "project:build",
    "ProjectID": "44c3daab4de35354e9e92df1696c57a0",
    "ProjectStateHash": "7601b243976cfdfa1e0f690e4720e58fc358ece7dd1d8c96c1209ed5133a3bb8",
    "StageCompletedAt": 3,
    "EarliestFatalError": 0,
    "StartTime": 1745655713072,
    "EndTime": 1745655827227,
    "PlaygroundUserID": 21453,
    "OperatingSystem": "win32",
    "UnityPackageID": null,
    "TargetPlatform": "develop",
    "UnityVersion": "2022.3.49f1",
    "LunaVersion": "6.2.1",
    "LogCount": 9,
    "Logs": [
        {
            "LogID": "5f6d3fa2-e19e-4681-a5f0-10cea1d9e611",
            "Order": 6,
            "Timestamp": 1745655827638,
            "Stage": 3,
            "ErrorType": 1,
            "ErrorCode": "LP3006",
            "Description": "You are not using the Luna API: Playable.InstallFullGame",
            "Details": [
                "You are not using the Luna API: Playable.InstallFullGame. Some ad networks require these calls. Please add these calls to ensure your playable works on all ad networks. Check documentation for more information."
            ],
            "DescriptionValues": [
                "Playable",
                "InstallFullGame"
            ],
            "DetailsValues": [
                "Playable",
                "InstallFullGame"
            ],
            "LogCount": 1,
            "LinePosition": null,
            "FilePath": "",
            "ClassName": "",
            "MemberName": "",
            "Severity": 0
        },
        {
            "LogID": "2d350aa7-4743-472c-936c-172aea47b9dd",
            "Order": 6,
            "Timestamp": 1745655827639,
            "Stage": 3,
            "ErrorType": 1,
            "ErrorCode": "LP3015",
            "Description": "You are not the Game Ended API: LifeCycle.GameEnded",
            "Details": [
                "You are not using the Game Ended API: LifeCycle.GameEnded. Some ad networks require this call, please add the event to avoid the ad being rejected."
            ],
            "DescriptionValues": [
                "LifeCycle",
                "GameEnded"
            ],
            "DetailsValues": [
                "LifeCycle",
                "GameEnded"
            ],
            "LogCount": 1,
            "LinePosition": null,
            "FilePath": "",
            "ClassName": "",
            "MemberName": "",
            "Severity": 0
        },
        {
            "LogID": "50718aaf-b859-43a9-a854-575d3a2a96e9",
            "Order": 6,
            "Timestamp": 1745655827640,
            "Stage": 3,
            "ErrorType": 3,
            "ErrorCode": "LP3007",
            "Description": "You are not using any custom events",
            "Details": [
                "You are not using any custom events. It is recommended to use custom events to have a better understanding of the playable."
            ],
            "DescriptionValues": [
                ""
            ],
            "DetailsValues": [
                ""
            ],
            "LogCount": 1,
            "LinePosition": null,
            "FilePath": "",
            "ClassName": "",
            "MemberName": "",
            "Severity": 0
        },
        {
            "LogID": "62a4d293-4701-461f-8366-1cae7e7f4009",
            "Order": 6,
            "Timestamp": 1745655827642,
            "Stage": 3,
            "ErrorType": 3,
            "ErrorCode": "LP3011",
            "Description": "You are not using any LunaPlaygroundFields attributes.",
            "Details": [
                "You are not using any LunaPlaygroundFields attributes, it allows you to configure your playable to different concepts to find the best variation, which can drastically improve playable performance on all ad networks."
            ],
            "DescriptionValues": null,
            "DetailsValues": null,
            "LogCount": 1,
            "LinePosition": null,
            "FilePath": "",
            "ClassName": "",
            "MemberName": "",
            "Severity": 0
        },
        {
            "LogID": "8fa81699-07d4-42bd-9ae1-0dcef0ce9a82",
            "Order": 0,
            "Timestamp": 1745655726278,
            "Stage": 1,
            "ErrorType": 0,
            "ErrorCode": "LP1006",
            "Description": "Linear color space is not supported",
            "Details": [
                "Due to compatibility reasons, Luna is only able to use Gamma color space for rendering. Please adjust your player settings."
            ],
            "DescriptionValues": [],
            "DetailsValues": [],
            "LogCount": 1,
            "LinePosition": 0,
            "FilePath": "",
            "ClassName": "",
            "MemberName": "",
            "Severity": 0
        },
        {
            "LogID": "1e88b604-169e-4fb8-859f-2305308dd696",
            "Order": 1,
            "Timestamp": 1745655726278,
            "Stage": 1,
            "ErrorType": 2,
            "ErrorCode": "LP1014",
            "Description": "We recommend running Runtime Analysis to find and remove all unused code",
            "Details": [
                "Navigate to the Runtime Analysis → Code tab to enable code stripping. Before uploading the playable, please make sure to have played all scenario’s of the playable in a development build to make Runtime Analysis work properly."
            ],
            "DescriptionValues": [],
            "DetailsValues": [],
            "LogCount": 1,
            "LinePosition": 0,
            "FilePath": "",
            "ClassName": "",
            "MemberName": "",
            "Severity": 0
        },
        {
            "LogID": "4616e4c1-df2c-4027-85e2-c18b4a7a8501",
            "Order": 2,
            "Timestamp": 1745655726279,
            "Stage": 1,
            "ErrorType": 2,
            "ErrorCode": "LP1016",
            "Description": "Extensive usage of ParticleSystem Component",
            "Details": [
                "There is extensive usage of the ParticleSystem component.\nExcessive usage of any component can be detrimental to performance on lower and in some cases higher end devices, consider reducing the amount the component is used.\nRecommended count: 10, current count 40."
            ],
            "DescriptionValues": [
                "ParticleSystem"
            ],
            "DetailsValues": [
                "ParticleSystem",
                "10",
                "40"
            ],
            "LogCount": 1,
            "LinePosition": 0,
            "FilePath": "",
            "ClassName": "",
            "MemberName": "",
            "Severity": 0
        },
        {
            "LogID": "07482c76-ed1e-42bf-8c93-23ef85360f5d",
            "Order": 3,
            "Timestamp": 1745655726291,
            "Stage": 1,
            "ErrorType": 0,
            "ErrorCode": "LP1015",
            "Description": "This TMP version is not fully supported",
            "Details": [
                "The incorrect Text Mesh Pro for this Unity version is in use, please update or downgrade to the recommended version {0} in the package manager. Go to Window → Package Manager"
            ],
            "DescriptionValues": [],
            "DetailsValues": [
                ""
            ],
            "LogCount": 1,
            "LinePosition": 0,
            "FilePath": "",
            "ClassName": "",
            "MemberName": "",
            "Severity": 0
        },
        {
            "LogID": "008c918a-2b60-4de6-ab2c-4aa9e2520a80",
            "Order": 4,
            "Timestamp": 1745655726291,
            "Stage": 1,
            "ErrorType": 0,
            "ErrorCode": "LP1032",
            "Description": "Package(s) is not supported in Luna",
            "Details": [
                "Currently package(s) com.unity.timeline are not supported in Luna. We recommend you to remove it and workaround it's functionality."
            ],
            "DescriptionValues": [
                "com.unity.timeline (1.7.6)"
            ],
            "DetailsValues": [
                "com.unity.timeline"
            ],
            "LogCount": 1,
            "LinePosition": 0,
            "FilePath": "D:/UnityPri/CardsDragons/Packages\\manifest.json",
            "ClassName": "",
            "MemberName": "",
            "Severity": 0
        }
    ]
}